LICENSE.txt
MANIFEST.in
README.md
baciphacs.py
setup.py
test.py
baciphacs.egg-info/PKG-INFO
baciphacs.egg-info/SOURCES.txt
baciphacs.egg-info/dependency_links.txt
baciphacs.egg-info/top_level.txt
doc/index.html