Metadata-Version: 1.1
Name: baciphacs
Version: 1.0
Summary: Bar Charts In Pure HTML And CSS
Home-page: https://github.com/tibonihoo/baciphacs
Author: Thibauld Nion
Author-email: thibauld@tibonihoo.net
License: BSD
Keywords: bar charts HTML CSS
Platform: All
Classifier: Development Status :: 5 - Production/Stable
Classifier: Intended Audience :: Developers
Classifier: License :: OSI Approved :: BSD License
Classifier: Operating System :: OS Independent
Classifier: Programming Language :: Python
Classifier: Topic :: Software Development :: Libraries :: Python Modules
